scorb_api/__init__.py
scorb_api/helpers/http.py
scorb_api/models/authorization.py
scorb_api/models/endpoint.py
scorb_api/models/endpoints/__init__.py
scorb_api/models/endpoints/endpoint_customizado.py
scorb_api/models/endpoints/entidade_customizadas/__init__.py
scorb_api/models/endpoints/entidade_de_cenario/__init__.py
scorb_api/models/endpoints/entidade_de_cenario/alert_definition.py
scorb_api/models/endpoints/entidade_de_cenario/cenario_visao.py
scorb_api/models/endpoints/entidade_de_cenario/centro_custo.py
scorb_api/models/endpoints/entidade_de_cenario/centro_custo_verba_valor_real.py
scorb_api/models/endpoints/entidade_de_cenario/check_caderias_total.py
scorb_api/models/endpoints/entidade_de_cenario/check_caderias_total_por_verba.py
scorb_api/models/endpoints/entidade_de_cenario/consulta_cadeira_fixo.py
scorb_api/models/endpoints/entidade_de_cenario/consulta_centro_de_custo_fixo_new.py
scorb_api/models/endpoints/entidade_de_cenario/consulta_centro_de_custo_fixo_old.py
scorb_api/models/endpoints/entidade_de_cenario/conta_contabil.py
scorb_api/models/endpoints/entidade_de_cenario/cotacao.py
scorb_api/models/endpoints/entidade_de_cenario/expressao_customizada.py
scorb_api/models/endpoints/entidade_de_cenario/faixa_salarial_esquema.py
scorb_api/models/endpoints/entidade_de_cenario/funcao_customizada.py
scorb_api/models/endpoints/entidade_de_cenario/funcionario.py
scorb_api/models/endpoints/entidade_de_cenario/funcionario_alocacao.py
scorb_api/models/endpoints/entidade_de_cenario/funcionario_salario_previsto.py
scorb_api/models/endpoints/entidade_de_cenario/grupo_centro_custo.py
scorb_api/models/endpoints/entidade_de_cenario/moeda.py
scorb_api/models/endpoints/entidade_de_cenario/plano_contas.py
scorb_api/models/endpoints/entidade_de_cenario/posicao.py
scorb_api/models/endpoints/entidade_de_cenario/reajuste_alcance_motivo.py
scorb_api/models/endpoints/entidade_de_cenario/report_calculated_field.py
scorb_api/models/endpoints/entidade_de_cenario/verba.py
scorb_api-0.1.9.dist-info/METADATA
scorb_api-0.1.9.dist-info/WHEEL
scorb_api-0.1.9.dist-info/licenses/LICENSE
scorb_api-0.1.9.dist-info/RECORD
